CHANGES.txt
LICENSE.txt
MANIFEST.in
README.md
README_pypi.txt
setup.py
docs/project_history.txt
iomanager/__init__.py
iomanager/iomanager.py
iomanager/web_tools.py
iomanager.egg-info/PKG-INFO
iomanager.egg-info/SOURCES.txt
iomanager.egg-info/dependency_links.txt
iomanager.egg-info/requires.txt
iomanager.egg-info/top_level.txt