Metadata-Version: 1.0
Name: iomanager
Version: 0.4.0
Summary: Guarantee structure and composition of input and output.
Home-page: https://github.com/jmatthias/iomanager
Author: Josh Matthias
Author-email: python.iomanager@gmail.com
License: LICENSE.txt
Platform: UNKNOWN
